blive/__init__.py
blive/core.py
blive/eeframework.py
blive/framework.py
blive/msg.py
blive-0.2.5.dist-info/LICENSE
blive-0.2.5.dist-info/WHEEL
blive-0.2.5.dist-info/METADATA
blive-0.2.5.dist-info/RECORD
