Metadata-Version: 2.1
Name: blive
Version: 0.2.5
Summary: 
License: MIT
Author: Cam
Author-email: yulinfeng000@gmail.com
Requires-Python: >=3.7,<4.0
Classifier: License :: OSI Approved :: MIT License
Classifier: Programming Language :: Python :: 3
Classifier: Programming Language :: Python :: 3.7
Classifier: Programming Language :: Python :: 3.8
Classifier: Programming Language :: Python :: 3.9
Classifier: Programming Language :: Python :: 3.10
Classifier: Programming Language :: Python :: 3.11
Requires-Dist: APScheduler (>=3.9.1.post1,<4.0.0)
Requires-Dist: aiodns (>=3.0.0,<4.0.0)
Requires-Dist: aiohttp (>=3.8.3,<4.0.0)
Requires-Dist: brotli (>=1.0.9,<2.0.0)
Requires-Dist: pyee (>=9.0.4,<10.0.0)
